[
    {
        "version": "v3",
        "date": "01.05.2021 12:00:01",
        "products": [
            {
                "name": "Молоко",
                "category": "Продукты",
                "price": "10",
                "count": "2",
                "actual_sum": "20"
            },
            {
                "name": "Хлеб",
                "category": "Продукты",
                "price": "10.03",
                "count": "2",
                "actual_sum": "20"
            }
        ],
        "counterparty": {
            "location": "Бовария, улица Центральная, дом 16",
            "typeo": "Общество с ограниченной ответственностью (ООО)",
            "name": "Магнит"
        },
        "currency": "₽",
        "actual_sum": "40"
    },
    {
        "version": "v3",
        "date": "01.05.2021 12:00:01",
        "positions": [
            {
                "name": "Молоко",
                "category": "Продукты",
                "price": "10",
                "count": "2",
                "actual_sum": "20",
                "transfers": {
                    "Активы": {
                        "Наличные": "-10"
                    },
                    "Пассивы": {
                        "Тинькофф кредитная карта": "10"
                    },
                    "Расходы": {
                        "Проживание": {
                            "Продукты": "20"
                        }
                    }
                }
            },
            {
                "name": "Хлеб",
                "category": "Продукты",
                "price": "10.03",
                "count": "2",
                "actual_sum": "20",
                "transfers": {
                    "Доходы": {
                        "Подарки": "20"
                    },
                    "Расходы": {
                        "Проживание": {
                            "Продукты": "20"
                        }
                    }
                }
            }
        ],
        "counterparty": {
            "location": "Бовария, улица Центральная, дом 16",
            "typeo": "Общество с ограниченной ответственностью (ООО)",
            "name": "Магнит"
        },
        "currency": "₽",
        "actual_sum": "40"
    },
    {
        "version": "v3",
        "date": "01.05.2021 12:00:01",
        "positions": [
            {
                "name": "Молоко",
                "price": "10",
                "count": "2",
                "actual_sum": "20",
                "transfers": {
                    "Активы": {
                        "Наличные": "-10"
                    },
                    "Пассивы": {
                        "Тинькофф кредитная карта": "10"
                    },
                    "Расходы": {
                        "Проживание": {
                            "Продукты": "20"
                        }
                    }
                }
            },
            {
                "name": "Хлеб",
                "price": "10.03",
                "count": "2",
                // "actual_sum": "20",
                "transfers": {
                    "Активы": {
                        "Наличные": {
                            "value": "-20",
                            "kind": "difference"
                        }
                    }
                }
            }
        ],
        "counterparty": {
            "location": "Бовария, улица Центральная, дом 16",
            "typeo": "Общество с ограниченной ответственностью (ООО)",
            "name": "Магнит"
        },
        "currency": "₽",
        "actual_sum": "40"
    },
    {
        "version": "v3",
        "date": "01.05.2021 12:00:01",
        "positions": [
            {
                "name": "Вася дал денег чтобы я купил хлеб",
                "price": "20",
                "count": "1",
                "transfers": {
                    "Активы": {
                        "Наличные": "20"
                    },
                    "Пассивы": {
                        "Обязательства": {
                            "Вася": "20"
                        }
                    }
                }
            }
        ]
    },
    {
        "version": "v3",
        "date": "01.05.2021 12:00:01",
        "positions": [
            {
                "name": "Дал Васе хлеб",
                "price": "20",
                "count": "1",
                "transfers": {
                    "Пассивы": {
                        "Обязательства": {
                            "Вася": {
                                "value": "-20",
                                "kind": "difference"
                            }
                        }
                    }
                }
            }
        ]
    },
    {
        "version": "v3",
        "date": "01.05.2021 13:00:01",
        "positions": [
            {
                "name": "Вася простил все долги",
                "transfers": {
                    "Пассивы": {
                        "Обязательства": {
                            "Вася": {
                                "value": "0",
                                "kind": "set"
                            }
                        }
                    }
                }
            }
        ]
    },
    {
        "date": "19.07.2020 22:09",
        "products": [
            {
                "name": "СОСИСКИ МЯСНЫЕ ПАПА",
                "category": "Продукты",
                "price": "169.00",
                "count": "1",
                "actual_sum": "169.00",
                "transfers": {
                    "Активы": {
                        "Наличные": {
                            "value": "-169.00",
                            "kind": "difference"
                        }
                    }
                }
            }
        ],
        "counterparty": {
            "location": "г.Москва,ул. Верхняя Первомайская  61",
            "typeo": "Акционерное общество (АО)",
            "name": "Дикси Юг"
        },
        "currency": "₽",
        "actual_sum": "169.00"
    },
    {
        "date": "06.03.2019 17:34",
        "products": [
            {
                "name": "БАНАНЫ ВЕС",
                "category": "Продукты",
                "price": "62.90",
                "count": "1.156",
                "actual_sum": "72.71"
            },
            {
                "name": "ЯЙЦО КУРИНОЕ ",
                "category": "Продукты",
                "price": "59.99",
                "count": "1",
                "actual_sum": "59.99"
            },
            {
                "name": "МОЛОКО ПРОСТАКВАШИНО ",
                "category": "Продукты",
                "price": "47.99",
                "count": "1",
                "actual_sum": "47.99"
            }
        ],
        "counterparty": {
            "location": "г.Москва,ул. Верхняя Первомайская  61",
            "typeo": "Акционерное общество (АО)",
            "name": "Дикси Юг"
        },
        "currency": "₽",
        "actual_sum": "180.69",
        "transfers":{
            "Активы":{
                "Наличные":{
                    "kind": "difference",
                    "value": "-180.69"
                }
            }
        }
    },
    {
        "version": "v3",
        "date": "01.05.2025 12:00:01",
        "counterparty":{
            "name": "Банк какой-то"
        },
        "check": {
            "positions":[
                {
                    "name": "Обмен валюты (покупка долларов за евро)",
                    "count": "100",
                    "price": "0.75",
                    "actual_sum": "75"
                }
            ],
            "currency": "€",
            "actual_sum": "75"
        },
        "transfers": {
            "Активы": {
                "Наличные": {
                    "Чёрный кошелёк": {
                        "€": {
                            "kind": "difference",
                            "value": "-75"
                        },
                        "$": {
                            "kind": "difference",
                            "value": "100"
                        }
                    }
                }
            }
        }
    },
    {
        "version": "another",
        "date": "2021-09-12 12:00:01T+04:00",

    }
]